{
    "parent": "minecraft:recipes/root",
    "criteria": {
        "has_dust": {
            "conditions": {
                "items": [
                    {
                        "items": "enchanting_reimagined:enchantment_dust"
                    }
                ]
            },
            "trigger": "minecraft:inventory_changed"
        },
        "has_the_recipe": {
            "conditions": {
                "recipe": "enchanting_reimagined:curse_scrubber"
            },
            "trigger": "minecraft:recipe_unlocked"
        }
    },
    "requirements": [
        [
            "has_the_recipe",
            "has_dust"
        ]
    ],
    "rewards": {
        "recipes": [
            "enchanting_reimagined:advanced_enchantment_dust"
        ]
    }
}